helpers/SGA.py
helpers/__init__.py
helpers/arbitraryNN.py
helpers/cross_validation.py
zangorth_helpers-1.3.6.dist-info/METADATA
zangorth_helpers-1.3.6.dist-info/WHEEL
zangorth_helpers-1.3.6.dist-info/top_level.txt
zangorth_helpers-1.3.6.dist-info/RECORD
