Metadata-Version: 2.1
Name: zangorth-helpers
Version: 1.3.6
Summary: Collection of helper functions for my projects
Home-page: https://github.com/Zangorth/Helpers
Author: Zangorth
License: UNKNOWN
Platform: UNKNOWN
Requires-Dist: pandas
Requires-Dist: scipy
Requires-Dist: torch
Requires-Dist: numpy
Requires-Dist: imbalanced-learn
Requires-Dist: imblearn
Requires-Dist: scikit-learn
